LICENSE
MANIFEST.in
README.md
setup.py
cnn_raccoon/__init__.py
cnn_raccoon.egg-info/PKG-INFO
cnn_raccoon.egg-info/SOURCES.txt
cnn_raccoon.egg-info/dependency_links.txt
cnn_raccoon.egg-info/top_level.txt
cnn_raccoon/graph/__init__.py
cnn_raccoon/graph/graph_builder.py
cnn_raccoon/keras/__init__.py
cnn_raccoon/keras/calculations.py
cnn_raccoon/keras/grad_cam.py
cnn_raccoon/keras/utils.py
cnn_raccoon/pytorch/__init__.py
cnn_raccoon/pytorch/calculations.py
cnn_raccoon/pytorch/grad_cam.py
cnn_raccoon/pytorch/model_weights.py
cnn_raccoon/pytorch/saliency_map.py
cnn_raccoon/pytorch/utils.py
cnn_raccoon/static/css/main.css
cnn_raccoon/static/images/logos/pytorch.png
cnn_raccoon/static/images/logos/tf.png
cnn_raccoon/static/images/project_template/image-holder.jpeg
cnn_raccoon/static/images/ui/Group 31.svg
cnn_raccoon/static/images/ui/Group 32.svg
cnn_raccoon/static/images/ui/Group 36.svg
cnn_raccoon/static/images/ui/cnn_logo.png
cnn_raccoon/static/images/ui/features_maps.svg
cnn_raccoon/static/images/ui/fp.png
cnn_raccoon/static/images/ui/grad_cam.png
cnn_raccoon/static/images/ui/saliency.png
cnn_raccoon/static/js/tabs.js
cnn_raccoon/templates/dashboard.html
cnn_raccoon/templates/template.html