Metadata-Version: 2.1
Name: cnn-raccoon
Version: 0.9.5
Summary: Create interactive dashboards for your Convolutional Neural Networks (CNNs) with a single line of code!
Home-page: https://github.com/lucko515/cnn-raccoon
Author: Luka Anicin
Author-email: luka.anicin@gmail.com
License: MIT
Platform: UNKNOWN
Classifier: Programming Language :: Python :: 3
Classifier: License :: OSI Approved :: MIT License
Classifier: Operating System :: OS Independent
Classifier: Intended Audience :: Education
Classifier: Intended Audience :: Developers
Classifier: Intended Audience :: Information Technology
Classifier: Intended Audience :: Science/Research
Requires-Python: >=3
